eff-1.0.0.dist-info/dependency_links.txt
eff-1.0.0.dist-info/entry_points.txt
eff-1.0.0.dist-info/METADATA
eff-1.0.0.dist-info/top_level.txt
eff-1.0.0.dist-info/WHEEL
eff/_core.py
eff/__init__.py
eff-1.0.0.dist-info/LICENSE
eff-1.0.0.dist-info/RECORD