Metadata-Version: 2.1
Name: eff
Version: 1.0.0
Project-URL: Homepage, https://github.com/orsinium-labs/eff
Author: Gram
Author-email: gram@orsinium.dev
Requires-Python: >=3.6
Classifier: License :: OSI Approved :: MIT License
